arsave/ML_Scores.py
arsave/__init__.py
arsave/introduction.py
arsave-0.0.1.dist-info/DESCRIPTION.rst
arsave-0.0.1.dist-info/METADATA
arsave-0.0.1.dist-info/RECORD
arsave-0.0.1.dist-info/WHEEL
arsave-0.0.1.dist-info/entry_points.txt
arsave-0.0.1.dist-info/metadata.json
arsave-0.0.1.dist-info/top_level.txt
