Metadata-Version: 2.0
Name: arsave
Version: 0.0.1
Summary: My own package
Home-page: UNKNOWN
Author: ClementTr
Author-email: clement.tailleur@gmail.com
License: WTFPL
Platform: UNKNOWN
Classifier: Programming Language :: Python
Classifier: Development Status :: 1 - Planning
Classifier: License :: OSI Approved
Classifier: Natural Language :: French
Classifier: Operating System :: OS Independent
Classifier: Programming Language :: Python :: 3.6
Classifier: Topic :: Sociology
